cli/__init__.py
cli/_version.py
cli/cli.py
cli/config.py
cli/helpers.py
cli/network.py
cli/shared_processing.py
cli/shared_queue.py
cli/utils.py
didimo_cli-2.7.0.dist-info/LICENSE
didimo_cli-2.7.0.dist-info/METADATA
didimo_cli-2.7.0.dist-info/WHEEL
didimo_cli-2.7.0.dist-info/entry_points.txt
didimo_cli-2.7.0.dist-info/top_level.txt
didimo_cli-2.7.0.dist-info/RECORD
