Metadata-Version: 2.1
Name: didimo-cli
Version: 2.7.0
Summary: Command-line interface to interact with Didimo API
Home-page: https://github.com/didimoinc/cli
Author: Didimo, Inc.
Author-email: support@didimo.co
License: Apache 2.0
Project-URL: Bug Reports, https://github.com/didimoinc/cli/issues
Project-URL: Source, https://github.com/didimoinc/cli
Keywords: cli,didimo,api
Classifier: License :: OSI Approved :: Apache Software License
Classifier: Development Status :: 5 - Production/Stable
Classifier: Environment :: Console
Classifier: Intended Audience :: Developers
Classifier: Natural Language :: English
Classifier: Topic :: Games/Entertainment
Classifier: Topic :: Multimedia :: Graphics
Classifier: Programming Language :: Python :: 3
License-File: LICENSE
Requires-Dist: click
Requires-Dist: requests
Requires-Dist: psutil
